LICENSE
README.md
dapodik_webservice/__init__.py
dapodik_webservice/__main__.py
dapodik_webservice/console/__init__.py
dapodik_webservice/console/console.py
dapodik_webservice/console/pengguna.py
dapodik_webservice/console/peserta_didik.py
dapodik_webservice/console/ptk.py
dapodik_webservice/console/rombongan_belajar.py
dapodik_webservice/console/sekolah.py
dapodik_webservice/console/util.py
dapodik_webservice/converter.py
dapodik_webservice/dapodik_webservice.py
dapodik_webservice/exception.py
dapodik_webservice/main.py
dapodik_webservice/models/__init__.py
dapodik_webservice/models/base.py
dapodik_webservice/models/pengguna.py
dapodik_webservice/models/peserta_didik.py
dapodik_webservice/models/ptk/__init__.py
dapodik_webservice/models/ptk/ptk.py
dapodik_webservice/models/ptk/rwy_kepangkatan.py
dapodik_webservice/models/ptk/rwy_pend_formal.py
dapodik_webservice/models/rombongan_belajar/__init__.py
dapodik_webservice/models/rombongan_belajar/anggota_rombel.py
dapodik_webservice/models/rombongan_belajar/pembelajaran.py
dapodik_webservice/models/rombongan_belajar/rombongan_belajar.py
dapodik_webservice/models/sekolah.py
dapodik_webservice/template/TEMPLATE.xlsx
dapodik_webservice/template/__init__.py
dapodik_webservice/typing.py
dapodik_webservice/util.py
dapodik_webservice/version.py
dapodik_webservice-3.1.0.dist-info/entry_points.txt
dapodik_webservice-3.1.0.dist-info/LICENSE
dapodik_webservice-3.1.0.dist-info/WHEEL
dapodik_webservice-3.1.0.dist-info/METADATA
dapodik_webservice-3.1.0.dist-info/RECORD
