Metadata-Version: 2.1
Name: dapodik-webservice
Version: 3.1.0
Summary: SDK Python Web Service aplikasi Dapodik
Home-page: https://dapodix.github.io/dapodik-webservice/
License: GPLv3
Author: hexatester
Author-email: habibrohman@protonmail.com
Requires-Python: >=3.6.1,<4.0.0
Classifier: Development Status :: 5 - Production/Stable
Classifier: Intended Audience :: Education
Classifier: License :: OSI Approved :: GNU General Public License v3 (GPLv3)
Classifier: License :: Other/Proprietary License
Classifier: Operating System :: OS Independent
Classifier: Programming Language :: Python
Classifier: Programming Language :: Python :: 3
Classifier: Programming Language :: Python :: 3.6
Classifier: Programming Language :: Python :: 3.7
Classifier: Programming Language :: Python :: 3.8
Classifier: Programming Language :: Python :: 3.9
Classifier: Topic :: Software Development :: Libraries :: Python Modules
Provides-Extra: excel
Requires-Dist: attrs (>=20.3.0,<21.0.0)
Requires-Dist: click (>=7.1.2,<8.0.0); extra == "excel"
Requires-Dist: openpyxl (>=3.0.5,<4.0.0); extra == "excel"
Requires-Dist: requests (>=2.25.1,<3.0.0)
Project-URL: Repository, https://github.com/dapodix/dapodik-webservice
